{
    "search_method_cls_name": "SimulatedAnnealingWithConstraint",
    "search_method_args": {
        "task_cls_name": "Harvester",
        "env_args": {
            "env_height": 8,
            "env_width": 8,
            "crashable": true,
            "leaps_behaviour": false,
            "max_calls": 10000
        },
        "exp_name": "search_debug",
        "search_method_args": {
            "initial_temperature": 100,
            "alpha": 0.9,
            "beta": 200
        },
        "max_evaluations": 1e6,
        "number_executions": 16,
        "search_seed": 1,
        "checkpoint_frequency": 1000,
        "n_proc": 1
    }
}